danta/__init__.py
danta/main.py
danta-0.1.0.dist-info/METADATA
danta-0.1.0.dist-info/WHEEL
danta-0.1.0.dist-info/entry_points.txt
danta-0.1.0.dist-info/RECORD
